volttron/client/__init__.py
volttron/client/commands/__init__.py
volttron/client/commands/auth_parser.py
volttron/client/commands/authz_parser.py
volttron/client/commands/config.py
volttron/client/commands/config_store_parser.py
volttron/client/commands/connection.py
volttron/client/commands/control.py
volttron/client/commands/install_agents.py
volttron/client/commands/rpc_parser.py
volttron/client/decorators.py
volttron/client/known_identities.py
volttron/client/logs.py
volttron/client/messaging/__init__.py
volttron/client/messaging/headers.py
volttron/client/messaging/health.py
volttron/client/messaging/topics.py
volttron/client/messaging/utils.py
volttron/client/vip/agent/__init__.py
volttron/client/vip/agent/core.py
volttron/client/vip/agent/decorators.py
volttron/client/vip/agent/dispatch.py
volttron/client/vip/agent/errors.py
volttron/client/vip/agent/example.py
volttron/client/vip/agent/results.py
volttron/client/vip/agent/subsystems/__init__.py
volttron/client/vip/agent/subsystems/auth.py
volttron/client/vip/agent/subsystems/base.py
volttron/client/vip/agent/subsystems/configstore.py
volttron/client/vip/agent/subsystems/health.py
volttron/client/vip/agent/subsystems/heartbeat.py
volttron/client/vip/agent/subsystems/hello.py
volttron/client/vip/agent/subsystems/peerlist.py
volttron/client/vip/agent/subsystems/ping.py
volttron/client/vip/agent/subsystems/pubsub.py
volttron/client/vip/agent/subsystems/query.py
volttron/client/vip/agent/subsystems/rpc.py
volttron/client/vip/agent/subsystems/web.py
volttron/client/vip/agent/utils.py
volttron/decorators.py
volttron/loader.py
volttron/py.typed
volttron/server/__init__.py
volttron/server/__main__.py
volttron/server/aip.py
volttron/server/async_.py
volttron/server/containers.py
volttron/server/decorators.py
volttron/server/logs.py
volttron/server/run_server.py
volttron/server/scheduling.py
volttron/server/server_argparser.py
volttron/server/server_options.py
volttron/server/server_ui.py
volttron_core-10.0.5rc6.dist-info/LICENSE
volttron_core-10.0.5rc6.dist-info/METADATA
volttron_core-10.0.5rc6.dist-info/WHEEL
volttron_core-10.0.5rc6.dist-info/entry_points.txt
volttron_core-10.0.5rc6.dist-info/RECORD
