Metadata-Version: 2.3
Name: volttron-core
Version: 10.0.5rc6
Summary: VOLTTRON™ is an open source platform for distributed sensing and control. The platform provides services for collecting and storing data from buildings and devices and provides an environment for developing applications which interact with that data.
License: Apache-2.0
Author: volttron
Author-email: volttron@pnnl.gov
Requires-Python: >=3.10,<4.0
Classifier: Development Status :: 3 - Alpha
Classifier: Intended Audience :: Developers
Classifier: Intended Audience :: Education
Classifier: License :: OSI Approved :: Apache Software License
Classifier: Programming Language :: Python
Classifier: Programming Language :: Python :: 3
Classifier: Programming Language :: Python :: 3.10
Classifier: Programming Language :: Python :: 3.11
Classifier: Programming Language :: Python :: 3.12
Classifier: Programming Language :: Python :: 3.13
Classifier: Topic :: Software Development :: Libraries :: Python Modules
Requires-Dist: PyYAML (>=6.0,<7.0)
Requires-Dist: blinker (>=1.7.0,<2.0.0)
Requires-Dist: cattrs (>=23.2.3,<24.0.0)
Requires-Dist: cryptography (>=43.0.1,<44.0.0)
Requires-Dist: dataclass-wizard (>=0.22.3,<0.23.0)
Requires-Dist: dateutils (>=0.6.12,<0.7.0)
Requires-Dist: deprecated (>=1.2.14,<2.0.0)
Requires-Dist: gevent (>=24.2.1,<24.3)
Requires-Dist: pip (>=24.0,<25.0)
Requires-Dist: poetry (>=1.8.2,<2.0.0)
Requires-Dist: psutil (>=5.9.0,<6.0.0)
Requires-Dist: pytest-mock (>=3.10.0,<4.0.0)
Requires-Dist: pytest-timeout (>=2.1.0,<3.0.0)
Requires-Dist: pyzmq (>=25.1.2,<26.0.0)
Requires-Dist: returns (>=0.22.0,<0.23.0)
Requires-Dist: toml (>=0.10.2,<0.11.0)
Requires-Dist: tzlocal (>=4.1,<5.0)
Requires-Dist: watchdog-gevent (>=0.1.1,<0.2.0)
Project-URL: Documentation, https://volttron.readthedocs.org
Project-URL: Homepage, https://volttron.org
Project-URL: Repository, https://github.com/eclipse-volttron/volttron-core
